Metadata-Version: 2.1
Name: passgenerator
Version: 1.0.4
Summary: A secure password generator with a CLI utility
Home-page: https://github.com/zloether/PassGenerator
Author: Zackary Loether
Author-email: zloether@gmail.com
License: MIT
Keywords: password generator
Platform: UNKNOWN
Classifier: Programming Language :: Python
Classifier: Programming Language :: Python :: 2
Classifier: Programming Language :: Python :: 2.6
Classifier: Programming Language :: Python :: 2.7
Classifier: Programming Language :: Python :: 3
Classifier: Programming Language :: Python :: 3.4
Classifier: Programming Language :: Python :: 3.5
Classifier: Programming Language :: Python :: 3.6
Classifier: Programming Language :: Python :: 3.7
Classifier: Topic :: Utilities
Classifier: License :: OSI Approved :: MIT License
Classifier: Development Status :: 5 - Production/Stable
